requests_unixsocket/__init__.py
requests_unixsocket/adapters.py
requests_unixsocket/tests/test_requests_unixsocket.py
requests_unixsocket/testutils.py
requests_unixsocket2-0.4.0.dist-info/LICENSE
requests_unixsocket2-0.4.0.dist-info/METADATA
requests_unixsocket2-0.4.0.dist-info/WHEEL
requests_unixsocket2-0.4.0.dist-info/RECORD
