Metadata-Version: 2.1
Name: requests-unixsocket2
Version: 0.4.0
Summary: Use requests to talk HTTP via a UNIX domain socket
Home-page: https://gitlab.com/thelabnyc/requests-unixsocket2
License: ISC
Author: thelab
Author-email: thelabdev@thelab.co
Requires-Python: >=3.9,<4.0
Classifier: Intended Audience :: Developers
Classifier: Intended Audience :: Information Technology
Classifier: License :: OSI Approved
Classifier: License :: OSI Approved :: Apache Software License
Classifier: Operating System :: OS Independent
Classifier: Programming Language :: Python
Classifier: Programming Language :: Python :: 3
Classifier: Programming Language :: Python :: 3.9
Classifier: Programming Language :: Python :: 3.10
Classifier: Programming Language :: Python :: 3.11
Classifier: Programming Language :: Python :: 3.12
Requires-Dist: requests (>=2.0.0,<3.0.0)
Requires-Dist: urllib3 (>=1.0,<3.0)
Project-URL: Repository, https://gitlab.com/thelabnyc/requests-unixsocket2
